odoo/addons/purchase_exception/README.rst
odoo/addons/purchase_exception/__init__.py
odoo/addons/purchase_exception/__manifest__.py
odoo/addons/purchase_exception/data/purchase_exception_data.xml
odoo/addons/purchase_exception/i18n/es.po
odoo/addons/purchase_exception/i18n/fr.po
odoo/addons/purchase_exception/i18n/it.po
odoo/addons/purchase_exception/i18n/pt_BR.po
odoo/addons/purchase_exception/i18n/purchase_exception.pot
odoo/addons/purchase_exception/i18n/zh_CN.po
odoo/addons/purchase_exception/models/__init__.py
odoo/addons/purchase_exception/models/exception_rule.py
odoo/addons/purchase_exception/models/purchase.py
odoo/addons/purchase_exception/models/purchase_line.py
odoo/addons/purchase_exception/readme/CONTRIBUTORS.md
odoo/addons/purchase_exception/readme/CREDITS.md
odoo/addons/purchase_exception/readme/DESCRIPTION.md
odoo/addons/purchase_exception/security/ir.model.access.csv
odoo/addons/purchase_exception/static/description/icon.png
odoo/addons/purchase_exception/static/description/index.html
odoo/addons/purchase_exception/tests/__init__.py
odoo/addons/purchase_exception/tests/test_purchase_exception.py
odoo/addons/purchase_exception/views/purchase_view.xml
odoo/addons/purchase_exception/wizard/__init__.py
odoo/addons/purchase_exception/wizard/purchase_exception_confirm.py
odoo/addons/purchase_exception/wizard/purchase_exception_confirm_view.xml
odoo_addon_purchase_exception-18.0.1.0.1.1.dist-info/METADATA
odoo_addon_purchase_exception-18.0.1.0.1.1.dist-info/WHEEL
odoo_addon_purchase_exception-18.0.1.0.1.1.dist-info/top_level.txt
odoo_addon_purchase_exception-18.0.1.0.1.1.dist-info/RECORD
